{
  "main": {
    "id": "4375a8a1d47b639e",
    "type": "split",
    "children": [
      {
        "id": "398580524569092b",
        "type": "tabs",
        "children": [
          {
            "id": "d14f8c70f2e117dc",
            "type": "leaf",
            "state": {
              "type": "markdown",
              "state": {
                "file": "Delivery - UberRoo.md",
                "mode": "source",
                "source": false
              }
            }
          }
        ]
      }
    ],
    "direction": "vertical"
  },
  "left": {
    "id": "7fb32e024c7c7aa7",
    "type": "split",
    "children": [
      {
        "id": "48037ea4ad35f1bb",
        "type": "tabs",
        "children": [
          {
            "id": "487335b03f753905",
            "type": "leaf",
            "state": {
              "type": "file-explorer",
              "state": {
                "sortOrder": "alphabetical"
              }
            }
          },
          {
            "id": "e412e0de946744dd",
            "type": "leaf",
            "state": {
              "type": "search",
              "state": {
                "query": "",
                "matchingCase": false,
                "explainSearch": false,
                "collapseAll": false,
                "extraContext": false,
                "sortOrder": "alphabetical"
              }
            }
          },
          {
            "id": "d29bab00b81ada9d",
            "type": "leaf",
            "state": {
              "type": "starred",
              "state": {}
            }
          }
        ]
      }
    ],
    "direction": "horizontal",
    "width": 200
  },
  "right": {
    "id": "44d32aecb431a261",
    "type": "split",
    "children": [
      {
        "id": "107e794e7ebd6a45",
        "type": "tabs",
        "children": [
          {
            "id": "b8340c48f120bc3b",
            "type": "leaf",
            "state": {
              "type": "backlink",
              "state": {
                "file": "Delivery - UberRoo.md",
                "collapseAll": false,
                "extraContext": false,
                "sortOrder": "alphabetical",
                "showSearch": false,
                "searchQuery": "",
                "backlinkCollapsed": false,
                "unlinkedCollapsed": true
              }
            }
          },
          {
            "id": "643255e0f749e5fd",
            "type": "leaf",
            "state": {
              "type": "outgoing-link",
              "state": {
                "file": "Delivery - UberRoo.md",
                "linksCollapsed": false,
                "unlinkedCollapsed": true
              }
            }
          },
          {
            "id": "10bc6ac8977a54ac",
            "type": "leaf",
            "state": {
              "type": "tag",
              "state": {
                "sortOrder": "frequency",
                "useHierarchy": true
              }
            }
          },
          {
            "id": "c6f3248ec574a660",
            "type": "leaf",
            "state": {
              "type": "outline",
              "state": {
                "file": "Delivery - UberRoo.md"
              }
            }
          }
        ]
      }
    ],
    "direction": "horizontal",
    "width": 300,
    "collapsed": true
  },
  "left-ribbon": {
    "hiddenItems": {
      "switcher:Open quick switcher": false,
      "graph:Open graph view": false,
      "canvas:Create new canvas": false,
      "daily-notes:Open today's daily note": false,
      "templates:Insert template": false,
      "command-palette:Open command palette": false,
      "obsidian-livesync:Replicate": false,
      "obsidian-livesync:Show log": false
    }
  },
  "active": "d14f8c70f2e117dc",
  "lastOpenFiles": [
    "Pasted image 20230428233210.png",
    "Delivery - UberRoo.md",
    "Ideas.md",
    "Delivery - UberRoo.md",
    "Delivery - UbeRoo.md",
    "Delivery - UberROO.md",
    "Delivery.md"
  ]
}